ibpythonic/__init__.py
ibpythonic/_version.py
ibpythonic/connection.py
ibpythonic/dispatcher.py
ibpythonic/message.py
ibpythonic/messagetools.py
ibpythonic/receiver.py
ibpythonic/sender.py
ibpythonic/lib/__init__.py
ibpythonic/lib/log.py
ibpythonic/lib/overloading.py
ibpythonic/sym/__init__.py
ibpythonic-0.1.6.dist-info/LICENSE
ibpythonic-0.1.6.dist-info/METADATA
ibpythonic-0.1.6.dist-info/WHEEL
ibpythonic-0.1.6.dist-info/top_level.txt
ibpythonic-0.1.6.dist-info/RECORD
