Metadata-Version: 1.2
Name: ibpythonic
Version: 0.1.6
Summary: IbPy-like interface for the Interactive Brokers Python API
Home-page: https://github.com/quantrocket-llc/ibpythonic
Maintainer: QuantRocket LLC
Maintainer-email: support@quantrocket.com
License: BSD License
Platform: UNKNOWN
